TCSP/__init__.py
TCSP-0.0.9.dist-info/LICENSE
TCSP-0.0.9.dist-info/METADATA
TCSP-0.0.9.dist-info/WHEEL
TCSP-0.0.9.dist-info/top_level.txt
TCSP-0.0.9.dist-info/RECORD
