Metadata-Version: 2.1
Name: TCSP
Version: 0.0.9
Summary: Traditional Chinese Stopwords and Punctuations Library
Home-page: UNKNOWN
Author: Bryan Wu
Author-email: bryanchw@umich.edu
License: MIT
Keywords: stopwords
Platform: UNKNOWN
Classifier: Development Status :: 5 - Production/Stable
Classifier: Intended Audience :: Education
Classifier: Operating System :: OS Independent
Classifier: License :: OSI Approved :: MIT License
Classifier: Programming Language :: Python :: 3
